mlpro_int_mujoco/__init__.py
mlpro_int_mujoco/envs/__init__.py
mlpro_int_mujoco/envs/cartpole.py
mlpro_int_mujoco/systems/__init__.py
mlpro_int_mujoco/systems/boxontable.xml
mlpro_int_mujoco/systems/cartpole.xml
mlpro_int_mujoco/systems/doublependulum.xml
mlpro_int_mujoco/systems/mlpro.xml
mlpro_int_mujoco/systems/pendulum.xml
mlpro_int_mujoco/systems/ur5.xml
mlpro_int_mujoco/systems/assets/mlpro/mesh/Arrow.stl
mlpro_int_mujoco/systems/assets/mlpro/mesh/X_letter.stl
mlpro_int_mujoco/systems/assets/mlpro/mesh/Y_letter.stl
mlpro_int_mujoco/systems/assets/mlpro/mesh/Z_letter.stl
mlpro_int_mujoco/systems/assets/mlpro/texture/logo.png
mlpro_int_mujoco/systems/assets/ur5/mesh/base.stl
mlpro_int_mujoco/systems/assets/ur5/mesh/forearm.stl
mlpro_int_mujoco/systems/assets/ur5/mesh/shoulder.stl
mlpro_int_mujoco/systems/assets/ur5/mesh/upperarm.stl
mlpro_int_mujoco/systems/assets/ur5/mesh/wrist1.stl
mlpro_int_mujoco/systems/assets/ur5/mesh/wrist2.stl
mlpro_int_mujoco/systems/assets/ur5/mesh/wrist3.stl
mlpro_int_mujoco/wrappers/__init__.py
mlpro_int_mujoco/wrappers/basics.py
mlpro_int_mujoco-1.0.3.dist-info/licenses/LICENSE
mlpro_int_mujoco-1.0.3.dist-info/METADATA
mlpro_int_mujoco-1.0.3.dist-info/WHEEL
mlpro_int_mujoco-1.0.3.dist-info/top_level.txt
mlpro_int_mujoco-1.0.3.dist-info/RECORD
