Metadata-Version: 2.4
Name: mlpro-int-mujoco
Version: 1.0.3
Summary: MLPro: Integration MuJoCo
Home-page: https://mlpro-int-mujoco.readthedocs.io
Author: MLPro Team
Author-email: mlpro@listen.fh-swf.de
Project-URL: Bug Tracker, https://mlpro-int-mujoco.readthedocs.io
Classifier: Programming Language :: Python :: 3
Classifier: License :: OSI Approved :: Apache Software License
Classifier: Operating System :: OS Independent
Requires-Python: >=3.11
License-File: LICENSE
Provides-Extra: full
Requires-Dist: mlpro[full]>=2.1.0; extra == "full"
Requires-Dist: mujoco>=3.1.2; extra == "full"
Requires-Dist: lxml>=4.9.2; extra == "full"
Dynamic: license-file
